llamadb3/__init__.py
llamadb3/connection.py
llamadb3/error_handler.py
llamadb3/query_builder.py
llamadb3_llamasearch-0.1.0.dist-info/licenses/LICENSE
llamadb3_llamasearch-0.1.0.dist-info/METADATA
llamadb3_llamasearch-0.1.0.dist-info/WHEEL
llamadb3_llamasearch-0.1.0.dist-info/top_level.txt
llamadb3_llamasearch-0.1.0.dist-info/RECORD
