Metadata-Version: 2.4
Name: llamadb3-llamasearch
Version: 0.1.0
Summary: Database management and query optimization library for Python
Home-page: https://llamasearch.ai
Author: LlamaSearch AI
Author-email: nikjois@llamasearch.ai
Classifier: Programming Language :: Python :: 3
Classifier: Programming Language :: Python :: 3.7
Classifier: Programming Language :: Python :: 3.8
Classifier: Programming Language :: Python :: 3.9
Classifier: Programming Language :: Python :: 3.10
Classifier: License :: OSI Approved :: MIT License
Classifier: Operating System :: OS Independent
Classifier: Topic :: Database
Classifier: Topic :: Software Development :: Libraries :: Python Modules
Requires-Python: >=3.7
License-File: LICENSE
Requires-Dist: typing_extensions; python_version < "3.8"
Provides-Extra: sqlite
Provides-Extra: mysql
Requires-Dist: pymysql>=1.0.2; extra == "mysql"
Provides-Extra: postgresql
Requires-Dist: psycopg2>=2.9.3; extra == "postgresql"
Provides-Extra: all
Requires-Dist: pymysql>=1.0.2; extra == "all"
Requires-Dist: psycopg2>=2.9.3; extra == "all"
Provides-Extra: dev
Requires-Dist: pytest>=7.0.0; extra == "dev"
Requires-Dist: pytest-cov>=3.0.0; extra == "dev"
Requires-Dist: black>=22.1.0; extra == "dev"
Requires-Dist: isort>=5.10.1; extra == "dev"
Requires-Dist: flake8>=4.0.1; extra == "dev"
Requires-Dist: mypy>=0.940; extra == "dev"
Dynamic: author
Dynamic: author-email
Dynamic: classifier
Dynamic: description
Dynamic: description-content-type
Dynamic: home-page
Dynamic: license-file
Dynamic: provides-extra
Dynamic: requires-dist
Dynamic: requires-python
Dynamic: summary
